ratesb_python/__init__.py
ratesb_python/common/__init__.py
ratesb_python/common/analyzer.py
ratesb_python/common/custom_classifier.py
ratesb_python/common/default_classifier.json
ratesb_python/common/messages.json
ratesb_python/common/reaction_data.py
ratesb_python/common/results.py
ratesb_python/common/temp.json
ratesb_python/common/util.py
ratesb_python-0.2.8.dist-info/licenses/LICENSE
ratesb_python-0.2.8.dist-info/METADATA
ratesb_python-0.2.8.dist-info/WHEEL
ratesb_python-0.2.8.dist-info/top_level.txt
ratesb_python-0.2.8.dist-info/RECORD
