Metadata-Version: 2.4
Name: ratesb_python
Version: 0.2.8
Summary: rate law analysis for systems biology
Home-page: https://github.com/sys-bio/ratesb_python
Author: Longxuan Fan
Author-email: Longxuan Fan <longxuan@usc.edu>
License: MIT License
Classifier: Programming Language :: Python :: 3
Classifier: Operating System :: OS Independent
Requires-Python: >=3.8
License-File: LICENSE
Requires-Dist: antimony
Requires-Dist: sbmlkinetics
Requires-Dist: sympy
Requires-Dist: python-libsbml
Dynamic: license-file
